activetigger/__init__.py
activetigger/__main__.py
activetigger/api.py
activetigger/datamodels.py
activetigger/frontend.py
activetigger/functions.py
activetigger/models.py
activetigger/server.py
activetigger/widget.py
activetigger/html/welcome.html
activetigger/img/active_tigger.png
activetigger-0.1.4.dist-info/LICENSE
activetigger-0.1.4.dist-info/WHEEL
activetigger-0.1.4.dist-info/METADATA
activetigger-0.1.4.dist-info/RECORD
