Metadata-Version: 2.1
Name: activetigger
Version: 0.1.4
Summary: ActiveTigger in Python
Author-email: Émilien Schultz - Julien Boelaert - Étienne Ollion <emilien.schultz@gmail.com>
Classifier: License :: OSI Approved :: MIT License
Requires-Dist: fastapi[all]
Requires-Dist: sentencepiece
Requires-Dist: requests
Requires-Dist: uvicorn
Requires-Dist: argparse
Requires-Dist: datasets
Requires-Dist: fasttext
Requires-Dist: ipywidgets
Requires-Dist: pyyaml
Requires-Dist: IPython
Requires-Dist: numpy
Requires-Dist: pandas
Requires-Dist: pyarrow
Requires-Dist: torch
Requires-Dist: transformers[torch]
Requires-Dist: sentence_transformers
Requires-Dist: typing-inspect
Requires-Dist: typing_extensions
Requires-Dist: spacy
Requires-Dist: pyyaml
Requires-Dist: protobuf
Requires-Dist: umap-learn
Requires-Dist: distinctipy
Requires-Dist: python-jose[cryptography]
Requires-Dist: bcrypt
Requires-Dist: plotly
Requires-Dist: matplotlib
Requires-Dist: scikit-learn
